ela/__init__.py
ela/_version.py
ela/classification.py
ela/io.py
ela/spatial.py
ela/textproc.py
ela/utils.py
ela/visual.py
ela/visual3d.py
ela/experiment/__init__.py
ela/experiment/textproc.py
ela/experiment/visual.py
ela-0.7.3.dist-info/LICENSE.txt
ela-0.7.3.dist-info/METADATA
ela-0.7.3.dist-info/WHEEL
ela-0.7.3.dist-info/top_level.txt
ela-0.7.3.dist-info/RECORD
