Metadata-Version: 2.1
Name: ela
Version: 0.7.3
Summary: A Python package for exploratory lithology analysis
Home-page: https://github.com/jmp75/pyela
Author: Jean-Michel Perraud, Juan Castilla
Author-email: per202@csiro.au
License: UNKNOWN
Project-URL: Bug Reports, https://github.com/jmp75/pyela/issues
Project-URL: Source, https://github.com/jmp75/pyela
Keywords: lithology geophysics groundwater data-mining
Platform: UNKNOWN
Classifier: Development Status :: 3 - Alpha
Classifier: Intended Audience :: Science/Research
Classifier: Topic :: Software Development :: Build Tools
Classifier: License :: OSI Approved :: MIT License
Classifier: Operating System :: OS Independent
Classifier: Programming Language :: Python
Classifier: Programming Language :: Python :: 3.6
Requires-Dist: pandas
Requires-Dist: geopandas
Requires-Dist: nltk
Requires-Dist: numpy
Requires-Dist: cartopy
Requires-Dist: mayavi
Requires-Dist: wordcloud
Requires-Dist: rasterio
Requires-Dist: scikit-learn
Requires-Dist: scipy
Requires-Dist: striplog
Requires-Dist: matplotlib
Requires-Dist: PyQt5 ; python_version >= "3.6"
